MANIFEST.in
pyproject.toml
setup.cfg
setup.py
django_mathactive.egg-info/PKG-INFO
django_mathactive.egg-info/SOURCES.txt
django_mathactive.egg-info/dependency_links.txt
django_mathactive.egg-info/requires.txt
django_mathactive.egg-info/top_level.txt
mathactive_django/__init__.py
mathactive_django/admin.py
mathactive_django/apps.py
mathactive_django/controllers.py
mathactive_django/env_loader.py
mathactive_django/generators.py
mathactive_django/hints.py
mathactive_django/logger.py
mathactive_django/models.py
mathactive_django/questions.py
mathactive_django/urls.py
mathactive_django/utils.py
mathactive_django/views.py
mathactive_django/data/difficulty_start_stop_step.csv
mathactive_django/data/question_templates.yaml
mathactive_django/microlessons/num_one.py
mathactive_django/migrations/0001_initial.py
mathactive_django/migrations/__init__.py